wiwi/__init__.py
wiwi/cmd.py
wiwi/version.py
wiwi-0.1.0.dev0.dist-info/DESCRIPTION.rst
wiwi-0.1.0.dev0.dist-info/entry_points.txt
wiwi-0.1.0.dev0.dist-info/METADATA
wiwi-0.1.0.dev0.dist-info/metadata.json
wiwi-0.1.0.dev0.dist-info/RECORD
wiwi-0.1.0.dev0.dist-info/top_level.txt
wiwi-0.1.0.dev0.dist-info/WHEEL
